ymler/__init__.py
ymler-0.0.1b0.dist-info/LICENSE
ymler-0.0.1b0.dist-info/METADATA
ymler-0.0.1b0.dist-info/WHEEL
ymler-0.0.1b0.dist-info/top_level.txt
ymler-0.0.1b0.dist-info/RECORD
